sqlmodel_celery_beat/__init__.py
sqlmodel_celery_beat/clockedschedule.py
sqlmodel_celery_beat/models.py
sqlmodel_celery_beat/schedulers.py
sqlmodel_celery_beat/tzcrontab.py
sqlmodel_celery_beat/util.py
sqlmodel_celery_beat-0.2.7.dist-info/LICENSE
sqlmodel_celery_beat-0.2.7.dist-info/METADATA
sqlmodel_celery_beat-0.2.7.dist-info/WHEEL
sqlmodel_celery_beat-0.2.7.dist-info/RECORD
