Metadata-Version: 2.1
Name: sqlmodel-celery-beat
Version: 0.2.7
Summary: A SQLModel based scheduler for Celery
License: MIT
Author: Alfred Rodenboog De Haas
Requires-Python: >=3.10,<4.0
Classifier: License :: OSI Approved :: MIT License
Classifier: Programming Language :: Python :: 3
Classifier: Programming Language :: Python :: 3.10
Classifier: Programming Language :: Python :: 3.11
Requires-Dist: celery (>=5.3.1,<6.0.0)
Requires-Dist: cron-descriptor (>=1.4.0,<2.0.0)
Requires-Dist: psycopg2-binary (>=2.9.6,<3.0.0)
Requires-Dist: pydantic (==2.7.3)
Requires-Dist: sqlmodel (>=0.0.19,<0.0.20)
